setup.py
distributions_ddg/Binomialdistribution.py
distributions_ddg/Gaussiandistribution.py
distributions_ddg/Generaldistribution.py
distributions_ddg/__init__.py
distributions_ddg.egg-info/PKG-INFO
distributions_ddg.egg-info/SOURCES.txt
distributions_ddg.egg-info/dependency_links.txt
distributions_ddg.egg-info/not-zip-safe
distributions_ddg.egg-info/top_level.txt