Metadata-Version: 1.0
Name: distributions-ddg
Version: 1.0
Summary: Gussian and Binomial distributions
Home-page: UNKNOWN
Author: DDuncan
Author-email: 942856733@qq.com
License: UNKNOWN
Platform: UNKNOWN
